bedrock_bio/__init__.py
bedrock_bio-1.0.0.dist-info/WHEEL
bedrock_bio-1.0.0.dist-info/entry_points.txt
bedrock_bio-1.0.0.dist-info/METADATA
bedrock_bio-1.0.0.dist-info/RECORD
