Metadata-Version: 2.3
Name: bedrock_bio
Version: 1.0.0
Summary: Curated datasets for computational biology workflows.
Author: Liam Abbott
Author-email: Liam Abbott <liam@bedrock.bio>
Requires-Dist: polars[fsspec,pandas]>=1.36.1
Requires-Python: >=3.10
